cloudstorageio/__init__.py
cloudstorageio/configs/__init__.py
cloudstorageio/configs/configs.py
cloudstorageio/configs/resources/__init__.py
cloudstorageio/enums/__init__.py
cloudstorageio/enums/enums.py
cloudstorageio/exceptions/__init__.py
cloudstorageio/exceptions/exceptions.py
cloudstorageio/interface/__init__.py
cloudstorageio/interface/async_cloud.py
cloudstorageio/interface/cloud_interface.py
cloudstorageio/interface/drop_box.py
cloudstorageio/interface/google_drive.py
cloudstorageio/interface/google_storage.py
cloudstorageio/interface/local_storage.py
cloudstorageio/interface/s3.py
cloudstorageio/log/__init__.py
cloudstorageio/tools/__init__.py
cloudstorageio/tools/ci_collections.py
cloudstorageio/tools/decorators.py
cloudstorageio/tools/logger.py
docs/__init__.py
docs/additional_docs.md
cloudstorageio-1.2.15.dist-info/LICENSE
cloudstorageio-1.2.15.dist-info/METADATA
cloudstorageio-1.2.15.dist-info/WHEEL
cloudstorageio-1.2.15.dist-info/top_level.txt
cloudstorageio-1.2.15.dist-info/RECORD
