Metadata-Version: 2.1
Name: cloudstorageio
Version: 1.2.15
Home-page: https://github.com/cognaize/cloudstorageio
Author: cognaize
License-File: LICENSE
Requires-Dist: boto3 >=1.4.7
Provides-Extra: all
Requires-Dist: dropbox >=9.4.0 ; extra == 'all'
Requires-Dist: pydrive >=1.3.1 ; extra == 'all'
Requires-Dist: google-cloud-storage >=1.14.0 ; extra == 'all'
Provides-Extra: drive
Requires-Dist: pydrive >=1.3.1 ; extra == 'drive'
Provides-Extra: dropbox
Requires-Dist: dropbox >=9.4.0 ; extra == 'dropbox'
Provides-Extra: google
Requires-Dist: google-cloud-storage >=1.14.0 ; extra == 'google'
